{
    "buckets": [
        {
            "Name": "main",
            "Source": "https://github.com/ScoopInstaller/Main.git",
            "Updated": "2026-05-17T20:35:39+00:00",
            "Manifests": 1540
        }
    ],
    "apps": [
        {
            "Info": "",
            "Version": "26.01",
            "Source": "main",
            "Updated": "2026-05-11T00:26:23.4093547+00:00",
            "Name": "7zip"
        },
        {
            "Info": "",
            "Version": "15.2.0",
            "Source": "main",
            "Updated": "2026-05-11T00:26:39.9068272+00:00",
            "Name": "gcc"
        },
        {
            "Info": "",
            "Version": "1.26.3",
            "Source": "main",
            "Updated": "2026-05-11T00:27:49.2790404+00:00",
            "Name": "go"
        },
        {
            "Info": "",
            "Version": "1.8.1",
            "Source": "main",
            "Updated": "2026-05-11T00:27:49.6115233+00:00",
            "Name": "jq"
        },
        {
            "Info": "",
            "Version": "16.1.0-rt_v14-rev0",
            "Source": "main",
            "Updated": "2026-05-11T00:28:39.4266263+00:00",
            "Name": "mingw"
        },
        {
            "Info": "",
            "Version": "26.1.0",
            "Source": "main",
            "Updated": "2026-05-11T00:28:48.3353233+00:00",
            "Name": "nodejs"
        },
        {
            "Info": "",
            "Version": "11.1.2",
            "Source": "main",
            "Updated": "2026-05-18T00:30:22.5535884+00:00",
            "Name": "pnpm"
        },
        {
            "Info": "",
            "Version": "3.51.1",
            "Source": "main",
            "Updated": "2026-05-18T00:30:24.0223417+00:00",
            "Name": "task"
        }
    ]
}
