{
    "buckets": [
        {
            "Name": "main",
            "Source": "https://github.com/ScoopInstaller/Main.git",
            "Updated": "2025-10-26T20:28:21+00:00",
            "Manifests": 1407
        }
    ],
    "apps": [
        {
            "Name": "7zip",
            "Version": "25.01",
            "Updated": "2025-10-20T00:09:57.549636+00:00",
            "Info": "",
            "Source": "main"
        },
        {
            "Name": "gcc",
            "Version": "13.2.0",
            "Updated": "2025-10-20T00:10:17.524654+00:00",
            "Info": "",
            "Source": "main"
        },
        {
            "Name": "go",
            "Version": "1.25.3",
            "Updated": "2025-10-20T00:11:27.8076879+00:00",
            "Info": "",
            "Source": "main"
        },
        {
            "Name": "jq",
            "Version": "1.8.1",
            "Updated": "2025-10-20T00:11:28.0838089+00:00",
            "Info": "",
            "Source": "main"
        },
        {
            "Name": "mingw",
            "Version": "15.2.0-rt_v13-rev0",
            "Updated": "2025-10-20T00:12:13.9374717+00:00",
            "Info": "",
            "Source": "main"
        },
        {
            "Name": "nodejs",
            "Version": "25.0.0",
            "Updated": "2025-10-20T00:12:30.2480083+00:00",
            "Info": "",
            "Source": "main"
        },
        {
            "Name": "pnpm",
            "Version": "10.19.0",
            "Updated": "2025-10-27T00:11:11.3353909+00:00",
            "Info": "",
            "Source": "main"
        },
        {
            "Name": "task",
            "Version": "3.45.4",
            "Updated": "2025-10-20T00:12:31.2835237+00:00",
            "Info": "",
            "Source": "main"
        }
    ]
}
